<?xml version="1.0" encoding="UTF-8"?>
<!DOCTYPE list SYSTEM "npc.dtd">
<list>
	<npc id="1600" name="Zinyanzi Agathion" title="">
		<set name="aggroRange" value="0" />
		<set name="ai_type" value="CharacterAI" />
		<set name="baseAtkRange" value="40" />
		<set name="baseAtkType" value="FIST" />
		<set name="baseCON" value="43" />
		<set name="baseCritRate" value="40" />
		<set name="baseDEX" value="30" />
		<set name="baseHpMax" value="680" />
		<set name="baseHpRate" value="1" />
		<set name="baseHpReg" value="0" />
		<set name="baseINT" value="21" />
		<set name="baseMAtk" value="265.02979" />
		<set name="baseMAtkSpd" value="333" />
		<set name="baseMDef" value="163.64727" />
		<set name="baseMEN" value="25" />
		<set name="baseMpMax" value="2000" />
		<set name="baseMpReg" value="0.9" />
		<set name="basePAtk" value="388.11142" />
		<set name="basePAtkSpd" value="253" />
		<set name="basePDef" value="223.6362" />
		<set name="baseRunSpd" value="120" />
		<set name="baseSTR" value="40" />
		<set name="baseShldDef" value="0" />
		<set name="baseShldRate" value="0" />
		<set name="baseWIT" value="20" />
		<set name="baseWalkSpd" value="30" />
		<set name="baseHitModify" value="5" />
		<set name="baseAvoidModify " value="0" />
		<set name="collision_height" value="5.5" />
		<set name="collision_radius" value="0.01" />
		<set name="corpse_time" value="7" />
		<set name="level" value="80" />
		<set name="rewardExp" value="0" />
		<set name="rewardRp" value="0" />
		<set name="rewardSp" value="0" />
		<set name="soulshot_count" value="2" />
		<set name="spiritshot_count" value="2" />
		<set name="texture" value="" />
		<set name="type" value="Npc" />
		<attributes>
			<defence attribute="fire" value="20" />
			<defence attribute="water" value="20" />
			<defence attribute="wind" value="20" />
			<defence attribute="earth" value="20" />
			<defence attribute="holy" value="20" />
			<defence attribute="unholy" value="20" />
		</attributes>
	</npc>
	<npc id="1601" name="Super Feline Queen Z" title="">
		<set name="aggroRange" value="0" />
		<set name="ai_type" value="CharacterAI" />
		<set name="baseAtkRange" value="40" />
		<set name="baseAtkType" value="FIST" />
		<set name="baseCON" value="37" />
		<set name="baseCritRate" value="40" />
		<set name="baseDEX" value="30" />
		<set name="baseHpMax" value="680" />
		<set name="baseHpRate" value="1" />
		<set name="baseHpReg" value="0" />
		<set name="baseINT" value="32" />
		<set name="baseMAtk" value="265.02979" />
		<set name="baseMAtkSpd" value="333" />
		<set name="baseMDef" value="163.64727" />
		<set name="baseMEN" value="25" />
		<set name="baseMpMax" value="2000" />
		<set name="baseMpReg" value="0.9" />
		<set name="basePAtk" value="388.11142" />
		<set name="basePAtkSpd" value="253" />
		<set name="basePDef" value="223.6362" />
		<set name="baseRunSpd" value="120" />
		<set name="baseSTR" value="35" />
		<set name="baseShldDef" value="0" />
		<set name="baseShldRate" value="0" />
		<set name="baseWIT" value="20" />
		<set name="baseWalkSpd" value="30" />
		<set name="baseHitModify" value="4.75" />
		<set name="baseAvoidModify " value="0" />
		<set name="collision_height" value="1.0" />
		<set name="collision_radius" value="1.0" />
		<set name="corpse_time" value="86400" />
		<set name="level" value="80" />
		<set name="rewardExp" value="0" />
		<set name="rewardRp" value="0" />
		<set name="rewardSp" value="0" />
		<set name="soulshot_count" value="2" />
		<set name="spiritshot_count" value="2" />
		<set name="texture" value="" />
		<set name="type" value="Npc" />
		<attributes>
			<defence attribute="fire" value="20" />
			<defence attribute="water" value="20" />
			<defence attribute="wind" value="20" />
			<defence attribute="earth" value="20" />
			<defence attribute="holy" value="20" />
			<defence attribute="unholy" value="20" />
		</attributes>
	</npc>
	<npc id="1602" name="Super Kat the Cat Z" title="">
		<set name="aggroRange" value="0" />
		<set name="ai_type" value="CharacterAI" />
		<set name="baseAtkRange" value="40" />
		<set name="baseAtkType" value="FIST" />
		<set name="baseCON" value="43" />
		<set name="baseCritRate" value="40" />
		<set name="baseDEX" value="30" />
		<set name="baseHpMax" value="680" />
		<set name="baseHpRate" value="1" />
		<set name="baseHpReg" value="0" />
		<set name="baseINT" value="21" />
		<set name="baseMAtk" value="265.02979" />
		<set name="baseMAtkSpd" value="333" />
		<set name="baseMDef" value="163.64727" />
		<set name="baseMEN" value="25" />
		<set name="baseMpMax" value="2000" />
		<set name="baseMpReg" value="0.9" />
		<set name="basePAtk" value="388.11142" />
		<set name="basePAtkSpd" value="253" />
		<set name="basePDef" value="223.6362" />
		<set name="baseRunSpd" value="120" />
		<set name="baseSTR" value="40" />
		<set name="baseShldDef" value="0" />
		<set name="baseShldRate" value="0" />
		<set name="baseWIT" value="20" />
		<set name="baseWalkSpd" value="30" />
		<set name="baseHitModify" value="4.75" />
		<set name="baseAvoidModify " value="0" />
		<set name="collision_height" value="1.0" />
		<set name="collision_radius" value="1.0" />
		<set name="corpse_time" value="86400" />
		<set name="level" value="80" />
		<set name="rewardExp" value="0" />
		<set name="rewardRp" value="0" />
		<set name="rewardSp" value="0" />
		<set name="soulshot_count" value="2" />
		<set name="spiritshot_count" value="2" />
		<set name="texture" value="" />
		<set name="type" value="Npc" />
		<attributes>
			<defence attribute="fire" value="20" />
			<defence attribute="water" value="20" />
			<defence attribute="wind" value="20" />
			<defence attribute="earth" value="20" />
			<defence attribute="holy" value="20" />
			<defence attribute="unholy" value="20" />
		</attributes>
	</npc>
	<npc id="1603" name="Super Mew the Cat Z" title="">
		<set name="aggroRange" value="0" />
		<set name="ai_type" value="CharacterAI" />
		<set name="baseAtkRange" value="40" />
		<set name="baseAtkType" value="FIST" />
		<set name="baseCON" value="40" />
		<set name="baseCritRate" value="40" />
		<set name="baseDEX" value="30" />
		<set name="baseHpMax" value="680" />
		<set name="baseHpRate" value="1" />
		<set name="baseHpReg" value="0" />
		<set name="baseINT" value="26" />
		<set name="baseMAtk" value="265.02979" />
		<set name="baseMAtkSpd" value="333" />
		<set name="baseMDef" value="163.64727" />
		<set name="baseMEN" value="25" />
		<set name="baseMpMax" value="2000" />
		<set name="baseMpReg" value="0.9" />
		<set name="basePAtk" value="388.11142" />
		<set name="basePAtkSpd" value="253" />
		<set name="basePDef" value="223.6362" />
		<set name="baseRunSpd" value="120" />
		<set name="baseSTR" value="38" />
		<set name="baseShldDef" value="0" />
		<set name="baseShldRate" value="0" />
		<set name="baseWIT" value="20" />
		<set name="baseWalkSpd" value="30" />
		<set name="baseHitModify" value="4.75" />
		<set name="baseAvoidModify " value="0" />
		<set name="collision_height" value="1.0" />
		<set name="collision_radius" value="1.0" />
		<set name="corpse_time" value="86400" />
		<set name="level" value="80" />
		<set name="rewardExp" value="0" />
		<set name="rewardRp" value="0" />
		<set name="rewardSp" value="0" />
		<set name="soulshot_count" value="2" />
		<set name="spiritshot_count" value="2" />
		<set name="texture" value="" />
		<set name="type" value="Npc" />
		<attributes>
			<defence attribute="fire" value="20" />
			<defence attribute="water" value="20" />
			<defence attribute="wind" value="20" />
			<defence attribute="earth" value="20" />
			<defence attribute="holy" value="20" />
			<defence attribute="unholy" value="20" />
		</attributes>
	</npc>
	<npc id="1604" name="Hanbok Agathion" title="">
		<set name="aggroRange" value="0" />
		<set name="ai_type" value="CharacterAI" />
		<set name="baseAtkRange" value="40" />
		<set name="baseAtkType" value="FIST" />
		<set name="baseCON" value="43" />
		<set name="baseCritRate" value="40" />
		<set name="baseDEX" value="30" />
		<set name="baseHpMax" value="680" />
		<set name="baseHpRate" value="1" />
		<set name="baseHpReg" value="0" />
		<set name="baseINT" value="21" />
		<set name="baseMAtk" value="265.02979" />
		<set name="baseMAtkSpd" value="333" />
		<set name="baseMDef" value="163.64727" />
		<set name="baseMEN" value="20" />
		<set name="baseMpMax" value="2000" />
		<set name="baseMpReg" value="0.9" />
		<set name="basePAtk" value="388.11142" />
		<set name="basePAtkSpd" value="253" />
		<set name="basePDef" value="223.6362" />
		<set name="baseRunSpd" value="120" />
		<set name="baseSTR" value="40" />
		<set name="baseShldDef" value="0" />
		<set name="baseShldRate" value="0" />
		<set name="baseWIT" value="20" />
		<set name="baseWalkSpd" value="30" />
		<set name="baseHitModify" value="5" />
		<set name="baseAvoidModify " value="0" />
		<set name="collision_height" value="5.5" />
		<set name="collision_radius" value="0.01" />
		<set name="corpse_time" value="7" />
		<set name="level" value="80" />
		<set name="rewardExp" value="0" />
		<set name="rewardRp" value="0" />
		<set name="rewardSp" value="0" />
		<set name="soulshot_count" value="2" />
		<set name="spiritshot_count" value="2" />
		<set name="texture" value="" />
		<set name="type" value="Npc" />
		<attributes>
			<defence attribute="fire" value="20" />
			<defence attribute="water" value="20" />
			<defence attribute="wind" value="20" />
			<defence attribute="earth" value="20" />
			<defence attribute="holy" value="20" />
			<defence attribute="unholy" value="20" />
		</attributes>
	</npc>
</list>
